notionsci/__main__.py
notionsci/cli/__init__.py
notionsci/cli/config.py
notionsci/cli/notion.py
notionsci/cli/sync/__init__.py
notionsci/cli/sync/markdown.py
notionsci/cli/sync/zotero.py
notionsci/config/__init__.py
notionsci/config/constants.py
notionsci/config/migrations.py
notionsci/config/structure.py
notionsci/connections/notion/__init__.py
notionsci/connections/notion/client.py
notionsci/connections/notion/helpers.py
notionsci/connections/notion/structures/__init__.py
notionsci/connections/notion/structures/blocks.py
notionsci/connections/notion/structures/common.py
notionsci/connections/notion/structures/content.py
notionsci/connections/notion/structures/properties.py
notionsci/connections/notion/structures/results.py
notionsci/connections/notion_unofficial/__init__.py
notionsci/connections/notion_unofficial/client.py
notionsci/connections/notion_unofficial/common.py
notionsci/connections/notion_unofficial/helpers.py
notionsci/connections/zotero/__init__.py
notionsci/connections/zotero/client.py
notionsci/connections/zotero/helpers.py
notionsci/connections/zotero/structures/__init__.py
notionsci/connections/zotero/structures/collection.py
notionsci/connections/zotero/structures/common.py
notionsci/connections/zotero/structures/item.py
notionsci/connections/zotero/structures/library.py
notionsci/connections/zotero/structures/query.py
notionsci/sync/__init__.py
notionsci/sync/structure.py
notionsci/sync/markdown/__init__.py
notionsci/sync/markdown/pages.py
notionsci/sync/zotero/__init__.py
notionsci/sync/zotero/base.py
notionsci/sync/zotero/collections.py
notionsci/sync/zotero/refs.py
notionsci/utils/__init__.py
notionsci/utils/dicts.py
notionsci/utils/io.py
notionsci/utils/iterators.py
notionsci/utils/markdown.py
notionsci/utils/serialization.py
notionsci-0.4.2.dist-info/LICENSE
notionsci-0.4.2.dist-info/METADATA
notionsci-0.4.2.dist-info/WHEEL
notionsci-0.4.2.dist-info/dependency_links.txt
notionsci-0.4.2.dist-info/entry_points.txt
notionsci-0.4.2.dist-info/pbr.json
notionsci-0.4.2.dist-info/top_level.txt
notionsci-0.4.2.dist-info/RECORD
